ec2imds/__init__.py
ec2imds/__main__.py
ec2imds/exceptions.py
ec2imds-0.0.3.dist-info/METADATA
ec2imds-0.0.3.dist-info/WHEEL
ec2imds-0.0.3.dist-info/licenses/COPYING
ec2imds-0.0.3.dist-info/RECORD
