Metadata-Version: 2.1
Name: ec2imds
Version: 0.0.3
Summary: ec2imds, the extensive EC2 Instance Meta Data Service(IMDS) tool
Project-URL: Homepage, https://github.com/si-magic/ec2imds
Project-URL: Issues, https://github.com/si-magic/ec2imds/issues
Author-email: David Timber <dxdt@dev.snart.me>
License-File: COPYING
Classifier: License :: OSI Approved :: GNU General Public License v3 (GPLv3)
Classifier: Operating System :: OS Independent
Classifier: Programming Language :: Python :: 3.11
Requires-Python: >=3.11
